{
  "users": [
    {
      "id": "3d44",
      "login": "Maksim",
      "password": "424991",
      "registed_at": "2033-08-08 16:10",
      "role_id": 0
    },
    {
      "id": "a50c",
      "login": "Ksenia",
      "password": "22218991",
      "registed_at": "2033-05-26 21:17",
      "role_id": 1
    }
  ],
  "roles": [
    {
      "id": "0",
      "name": "Администратор"
    },
    {
      "id": "1",
      "name": "Модератор"
    },
    {
      "id": "2",
      "name": "Читатель"
    },
    {
      "id": "3",
      "name": "Гость"
    }
  ],
  "posts": [
    {
      "id": "001",
      "title": "Выжить на проекте",
      "image_url": "https://fastly.picsum.photos/id/312/200/150.jpg?hmac=yWUF9LZxGJ9kHya30hlC6otE3fN1PmlXJYymb0yQhH8",
      "content": "Принимая во внимание показатели успешности, курс на социально-ориентированный национальный проект обеспечивает актуальность новых предложений. Прежде всего, экономическая повестка сегодняшнего дня создаёт предпосылки для прогресса профессионального сообщества. Но стремящиеся вытеснить традиционное производство, нанотехнологии являются только методом политического участия и представлены в исключительно положительном свете. Не следует, однако, забывать, что семантический разбор внешних противодействий, в своём классическом представлении, допускает внедрение системы массового участия. <br><br>Не следует, однако, забывать, что современная методология разработки позволяет выполнить важные задания по разработке инновационных методов управления процессами. Противоположная точка зрения подразумевает, что реплицированные с зарубежных источников, современные исследования разоблачены. Лишь действия представителей оппозиции призваны к ответу. Но высокое качество позиционных исследований требует определения и уточнения переосмысления внешнеэкономических политик. Наше дело не так однозначно, как может показаться: новая модель организационной деятельности прекрасно подходит для реализации существующих финансовых и административных условий.<br><br>И нет сомнений, что элементы политического процесса представляют собой не что иное, как квинтэссенцию победы маркетинга над разумом и должны быть призваны к ответу. Таким образом, перспективное планирование играет важную роль в формировании системы массового участия. Каждый из нас понимает очевидную вещь: консультация с широким активом в значительной степени обусловливает важность благоприятных перспектив.",
      "published_at": "24.07.1977"
    },
    {
      "id": "002",
      "title": "О том, что было",
      "image_url": "https://fastly.picsum.photos/id/616/200/150.jpg?hmac=aNmJHWriDzVH6bcT_uUP9J7LM48RGO9m9wl_X8o_V3Y",
      "content": "Принимая во внимание показатели успешности, курс на социально-ориентированный национальный проект обеспечивает актуальность новых предложений. Прежде всего, экономическая повестка сегодняшнего дня создаёт предпосылки для прогресса профессионального сообщества. Но стремящиеся вытеснить традиционное производство, нанотехнологии являются только методом политического участия и представлены в исключительно положительном свете. Не следует, однако, забывать, что семантический разбор внешних противодействий, в своём классическом представлении, допускает внедрение системы массового участия.<br><br>Не следует, однако, забывать, что современная методология разработки позволяет выполнить важные задания по разработке инновационных методов управления процессами. Противоположная точка зрения подразумевает, что реплицированные с зарубежных источников, современные исследования разоблачены. Лишь действия представителей оппозиции призваны к ответу. Но высокое качество позиционных исследований требует определения и уточнения переосмысления внешнеэкономических политик. Наше дело не так однозначно, как может показаться: новая модель организационной деятельности прекрасно подходит для реализации существующих финансовых и административных условий.<br><br>И нет сомнений, что элементы политического процесса представляют собой не что иное, как квинтэссенцию победы маркетинга над разумом и должны быть призваны к ответу. Таким образом, перспективное планирование играет важную роль в формировании системы массового участия. Каждый из нас понимает очевидную вещь: консультация с широким активом в значительной степени обусловливает важность благоприятных перспектив.",
      "published_at": "24.07.1955"
    },
    {
      "id": "003",
      "title": "О том чего не было",
      "image_url": "https://fastly.picsum.photos/id/656/200/150.jpg?hmac=9E0NswLS7VgycV9LS5lNQgN6IFh_9J_8UjFJZqHgn_A",
      "content": "Принимая во внимание показатели успешности, курс на социально-ориентированный национальный проект обеспечивает актуальность новых предложений. Прежде всего, экономическая повестка сегодняшнего дня создаёт предпосылки для прогресса профессионального сообщества. Но стремящиеся вытеснить традиционное производство, нанотехнологии являются только методом политического участия и представлены в исключительно положительном свете. Не следует, однако, забывать, что семантический разбор внешних противодействий, в своём классическом представлении, допускает внедрение системы массового участия.<br><br>Не следует, однако, забывать, что современная методология разработки позволяет выполнить важные задания по разработке инновационных методов управления процессами. Противоположная точка зрения подразумевает, что реплицированные с зарубежных источников, современные исследования разоблачены. Лишь действия представителей оппозиции призваны к ответу. Но высокое качество позиционных исследований требует определения и уточнения переосмысления внешнеэкономических политик. Наше дело не так однозначно, как может показаться: новая модель организационной деятельности прекрасно подходит для реализации существующих финансовых и административных условий.<br><br>И нет сомнений, что элементы политического процесса представляют собой не что иное, как квинтэссенцию победы маркетинга над разумом и должны быть призваны к ответу. Таким образом, перспективное планирование играет важную роль в формировании системы массового участия. Каждый из нас понимает очевидную вещь: консультация с широким активом в значительной степени обусловливает важность благоприятных перспектив.",
      "published_at": "24.07.1934"
    },
    {
      "id": "004",
      "title": "Где бы мы могли с тобой быть",
      "image_url": "https://fastly.picsum.photos/id/574/200/150.jpg?hmac=m2qRDlsTFnzwngxVwcLRYI_6dS2Hwl20DACWNefufZ0",
      "content": "Принимая во внимание показатели успешности, курс на социально-ориентированный национальный проект обеспечивает актуальность новых предложений. Прежде всего, экономическая повестка сегодняшнего дня создаёт предпосылки для прогресса профессионального сообщества. Но стремящиеся вытеснить традиционное производство, нанотехнологии являются только методом политического участия и представлены в исключительно положительном свете. Не следует, однако, забывать, что семантический разбор внешних противодействий, в своём классическом представлении, допускает внедрение системы массового участия.<br><br>Не следует, однако, забывать, что современная методология разработки позволяет выполнить важные задания по разработке инновационных методов управления процессами. Противоположная точка зрения подразумевает, что реплицированные с зарубежных источников, современные исследования разоблачены. Лишь действия представителей оппозиции призваны к ответу. Но высокое качество позиционных исследований требует определения и уточнения переосмысления внешнеэкономических политик. Наше дело не так однозначно, как может показаться: новая модель организационной деятельности прекрасно подходит для реализации существующих финансовых и административных условий.<br><br>И нет сомнений, что элементы политического процесса представляют собой не что иное, как квинтэссенцию победы маркетинга над разумом и должны быть призваны к ответу. Таким образом, перспективное планирование играет важную роль в формировании системы массового участия. Каждый из нас понимает очевидную вещь: консультация с широким активом в значительной степени обусловливает важность благоприятных перспектив.",
      "published_at": "24.07.1945"
    },
    {
      "id": "005",
      "title": "Чего не стоит бояться",
      "image_url": "https://fastly.picsum.photos/id/840/200/150.jpg?hmac=ZbZkpTdQm7NxQ7wCXfENZX76FA9oV_eYI8W01-4TYmU",
      "content": "Принимая во внимание показатели успешности, курс на социально-ориентированный национальный проект обеспечивает актуальность новых предложений. Прежде всего, экономическая повестка сегодняшнего дня создаёт предпосылки для прогресса профессионального сообщества. Но стремящиеся вытеснить традиционное производство, нанотехнологии являются только методом политического участия и представлены в исключительно положительном свете. Не следует, однако, забывать, что семантический разбор внешних противодействий, в своём классическом представлении, допускает внедрение системы массового участия.<br><br>Не следует, однако, забывать, что современная методология разработки позволяет выполнить важные задания по разработке инновационных методов управления процессами. Противоположная точка зрения подразумевает, что реплицированные с зарубежных источников, современные исследования разоблачены. Лишь действия представителей оппозиции призваны к ответу. Но высокое качество позиционных исследований требует определения и уточнения переосмысления внешнеэкономических политик. Наше дело не так однозначно, как может показаться: новая модель организационной деятельности прекрасно подходит для реализации существующих финансовых и административных условий.<br><br>И нет сомнений, что элементы политического процесса представляют собой не что иное, как квинтэссенцию победы маркетинга над разумом и должны быть призваны к ответу. Таким образом, перспективное планирование играет важную роль в формировании системы массового участия. Каждый из нас понимает очевидную вещь: консультация с широким активом в значительной степени обусловливает важность благоприятных перспектив.",
      "published_at": "24.07.1987"
    },
    {
      "id": "006",
      "title": "О чем стоит задуматься",
      "image_url": "https://fastly.picsum.photos/id/216/200/150.jpg?hmac=rV0q_dGb0l972dwoG8owjvh4XPbym7FNPsZx2JvzIJk",
      "content": "Принимая во внимание показатели успешности, курс на социально-ориентированный национальный проект обеспечивает актуальность новых предложений. Прежде всего, экономическая повестка сегодняшнего дня создаёт предпосылки для прогресса профессионального сообщества. Но стремящиеся вытеснить традиционное производство, нанотехнологии являются только методом политического участия и представлены в исключительно положительном свете. Не следует, однако, забывать, что семантический разбор внешних противодействий, в своём классическом представлении, допускает внедрение системы массового участия.<br><br>Не следует, однако, забывать, что современная методология разработки позволяет выполнить важные задания по разработке инновационных методов управления процессами. Противоположная точка зрения подразумевает, что реплицированные с зарубежных источников, современные исследования разоблачены. Лишь действия представителей оппозиции призваны к ответу. Но высокое качество позиционных исследований требует определения и уточнения переосмысления внешнеэкономических политик. Наше дело не так однозначно, как может показаться: новая модель организационной деятельности прекрасно подходит для реализации существующих финансовых и административных условий.<br><br>И нет сомнений, что элементы политического процесса представляют собой не что иное, как квинтэссенцию победы маркетинга над разумом и должны быть призваны к ответу. Таким образом, перспективное планирование играет важную роль в формировании системы массового участия. Каждый из нас понимает очевидную вещь: консультация с широким активом в значительной степени обусловливает важность благоприятных перспектив.",
      "published_at": "24.07.1921"
    },
    {
      "id": "007",
      "title": "Что необходимо ценить",
      "image_url": "https://fastly.picsum.photos/id/317/200/150.jpg?hmac=6zaJH-wvEbYmSYJ9S2YTBAITHwODuYbTEx_ywed70Fw",
      "content": "Принимая во внимание показатели успешности, курс на социально-ориентированный национальный проект обеспечивает актуальность новых предложений. Прежде всего, экономическая повестка сегодняшнего дня создаёт предпосылки для прогресса профессионального сообщества. Но стремящиеся вытеснить традиционное производство, нанотехнологии являются только методом политического участия и представлены в исключительно положительном свете. Не следует, однако, забывать, что семантический разбор внешних противодействий, в своём классическом представлении, допускает внедрение системы массового участия.<br><br>Не следует, однако, забывать, что современная методология разработки позволяет выполнить важные задания по разработке инновационных методов управления процессами. Противоположная точка зрения подразумевает, что реплицированные с зарубежных источников, современные исследования разоблачены. Лишь действия представителей оппозиции призваны к ответу. Но высокое качество позиционных исследований требует определения и уточнения переосмысления внешнеэкономических политик. Наше дело не так однозначно, как может показаться: новая модель организационной деятельности прекрасно подходит для реализации существующих финансовых и административных условий.<br><br>И нет сомнений, что элементы политического процесса представляют собой не что иное, как квинтэссенцию победы маркетинга над разумом и должны быть призваны к ответу. Таким образом, перспективное планирование играет важную роль в формировании системы массового участия. Каждый из нас понимает очевидную вещь: консультация с широким активом в значительной степени обусловливает важность благоприятных перспектив.",
      "published_at": "24.07.1946"
    },
    {
      "id": "008",
      "title": "Как можно это все заменить",
      "image_url": "https://fastly.picsum.photos/id/459/200/150.jpg?hmac=6g5RzlLaxaVLQ3ccP-DBJ8x81ZSoePIkEc2cGOcuDwo",
      "content": "Принимая во внимание показатели успешности, курс на социально-ориентированный национальный проект обеспечивает актуальность новых предложений. Прежде всего, экономическая повестка сегодняшнего дня создаёт предпосылки для прогресса профессионального сообщества. Но стремящиеся вытеснить традиционное производство, нанотехнологии являются только методом политического участия и представлены в исключительно положительном свете. Не следует, однако, забывать, что семантический разбор внешних противодействий, в своём классическом представлении, допускает внедрение системы массового участия.<br><br>Не следует, однако, забывать, что современная методология разработки позволяет выполнить важные задания по разработке инновационных методов управления процессами. Противоположная точка зрения подразумевает, что реплицированные с зарубежных источников, современные исследования разоблачены. Лишь действия представителей оппозиции призваны к ответу. Но высокое качество позиционных исследований требует определения и уточнения переосмысления внешнеэкономических политик. Наше дело не так однозначно, как может показаться: новая модель организационной деятельности прекрасно подходит для реализации существующих финансовых и административных условий.<br><br>И нет сомнений, что элементы политического процесса представляют собой не что иное, как квинтэссенцию победы маркетинга над разумом и должны быть призваны к ответу. Таким образом, перспективное планирование играет важную роль в формировании системы массового участия. Каждый из нас понимает очевидную вещь: консультация с широким активом в значительной степени обусловливает важность благоприятных перспектив.",
      "published_at": "24.07.1934"
    }
  ],
  "comments": [
    {
      "id": "4900",
      "author_id": "3d44",
      "post_id": "001",
      "published_at": "2033-08-16 10:07",
      "content": "My first comment"
    },
    {
      "id": "54f0",
      "author_id": "3d44",
      "post_id": "001",
      "published_at": "2033-08-13 10:47",
      "content": "My first comment1\n"
    },
    {
      "id": "a5d9",
      "author_id": "3d44",
      "post_id": "001",
      "published_at": "2033-06-17 02:57",
      "content": "My first comment12\n"
    },
    {
      "id": "23eb",
      "author_id": "3d44",
      "post_id": "001",
      "published_at": "2033-07-08 04:39",
      "content": "My first comment123\n"
    },
    {
      "id": "a2f4",
      "author_id": "3d44",
      "post_id": "001",
      "published_at": "2033-05-26 16:24",
      "content": "My first comment1234\n"
    },
    {
      "id": "5421",
      "author_id": "3d44",
      "post_id": "001",
      "published_at": "2033-09-06 07:14",
      "content": "New comment"
    }
  ],
  "sessions": [
    {
      "id": "c2e0",
      "hash": "0.24577374598392220939047092542750760912895202636719",
      "user": {
        "id": "3d44",
        "login": "Maksim",
        "password": "424991",
        "registeredAt": "2033-08-08 16:10",
        "roleId": 0
      }
    },
    {
      "id": "985f",
      "hash": "0.87452347283798004262678205122938379645347595214844",
      "user": {
        "id": "3d44",
        "login": "Maksim",
        "password": "424991",
        "registeredAt": "2033-08-08 16:10",
        "roleId": 0
      }
    }
  ]
}